HAPRA/Hapra2/2.1c_signals/signals_tb.vhdl
library ieee;
use ieee.std_logic_1164.all;

entity signals_tb is
end signals_tb;

architecture test of signals_tb is
  signal a, b, c : std_logic;
begin
  process begin
    -- dies sind nur Beispiel für Tupel die nicht verwendet werden muessen
    -- insgesamt sollen 8 verschiedene Tupel ausgewaehlt werden
    -- Beispiel für ein Tupel mit 2 unterschiedlichen Signalwerten
    a <= 'X';
    b <= 'W';
    wait for 10 ns; -- Ansonsten werden die Zuordnungen für a, b und c gleichzeitig ausgeführt
    c <= a and b;		
    wait for 10 ns; -- Gibt ein Zeitfenster für die Beobachtung der Ausgabe von a und b im GTK Wave
    c <= a or b;		
    wait for 10 ns; -- Gibt ein Zeitfenster für die Beobachtung der Ausgabe von a oder b im GTK Wave
    -- Das Tupel (0,1) das auf jeden Fall ausgewertet werden soll
    a <= '0';
    b <= '1';
    wait for 10 ns;
    c <= a and b;		--c ist 0
    wait for 10 ns;
    c <= a or b;		--c ist 1
    wait for 10 ns;
    -- Ab hier folgen die eigenen Paare
    
    a <= '1';
    b <= '0';
    wait for 10 ns;
    c <= a and b;		--c ist 0
    wait for 10 ns;
    c <= a or b;		--c ist 1
    wait for 10 ns;
    
    a <= 'X';
    b <= '1';
    wait for 10 ns;
    c <= a and b;		--c ist X
    wait for 10 ns;
    c <= a or b;		--c ist 1
    wait for 10 ns;
    
    a <= 'H';
    b <= 'L';
    wait for 10 ns;
    c <= a and b;		--c ist 0
    wait for 10 ns;
    c <= a or b;		--c ist 1
    wait for 10 ns;
    
    a <= 'Z';
    b <= 'W';
    wait for 10 ns;
    c <= a and b;		--c ist X
    wait for 10 ns;
    c <= a or b;		--c ist X
    wait for 10 ns;
    
    a <= 'L';
    b <= 'X';
    wait for 10 ns;
    c <= a and b;		--c ist 0
    wait for 10 ns;
    c <= a or b;		--c ist X
    wait for 10 ns;
    
    a <= 'W';
    b <= 'H';
    wait for 10 ns;
    c <= a and b;		--c ist X
    wait for 10 ns;
    c <= a or b;		--c ist 1
    wait for 10 ns;
    
    a <= '0';
    b <= 'Z';
    wait for 10 ns;
    c <= a and b;		--c ist 0
    wait for 10 ns;
    c <= a or b;		--c ist X
    wait for 10 ns;
    
    a <= 'L';
    b <= '1';
    wait for 10 ns;
    c <= a and b;		--c ist 0
    wait for 10 ns;
    c <= a or b;		--c ist 1
    wait for 10 ns;
    
    
    -- Beispiele für Tupel die nicht verwendet werden sollten 
    -- (0,1) und (1,0) sind das gleiche Tupel, es sollte also nur eins davon verwendet werden
    a <= '1';
    b <= '0';
    -- (0,0) hat die gleichen Signalwerte, sollte also nicht verwendet werden
    a <= '0';
    b <= '0';
    -- (1,1) hat die gleichen Signalwerte, sollte also nicht verwendet werden
    a <= '1';
    b <= '1';
    assert false report "End of test";
    wait;
  end process;
end test;

HAPRA/Hapra2/2.1c_signals/testbench.vcd
$date
  Wed Oct 23 14:25:19 2024
$end
$version
  GHDL v0
$end
$timescale
  1 fs
$end
$scope module standard $end
$upscope $end
$scope module std_logic_1164 $end
$upscope $end
$scope module signals_tb $end
$var reg 1 ! a $end
$var reg 1 " b $end
$var reg 1 # c $end
$upscope $end
$enddefinitions $end
#0
X!
W"
U#
#10000000
X#
#20000000
#30000000
0!
1"
#40000000
0#
#50000000
1#
#60000000
1!
0"
#70000000
0#
#80000000
1#
#90000000
X!
1"
#100000000
X#
#110000000
1#
#120000000
H!
L"
#130000000
0#
#140000000
1#
#150000000
Z!
W"
#160000000
X#
#170000000
#180000000
L!
X"
#190000000
0#
#200000000
X#
#210000000
W!
H"
#220000000
#230000000
1#
#240000000
0!
Z"
#250000000
0#
#260000000
X#
#270000000
L!
1"
#280000000
0#
#290000000
1#
#300000000
1!
