HAPRA/Hapra9/alu/alu.vhdl
-- Some portions of this code are based on code from the book "Digital Design and Computer Architecture" by Harris and Harris.
-- For educational purposes in TU Dortmund only.

library ieee;
use ieee.std_logic_1164.all;
use ieee.numeric_std.all;

entity alu is
  port(
    a: in std_logic_vector(31 downto 0);
    b: in std_logic_vector(31 downto 0);
    alucontrol: in std_logic_vector(2 downto 0);
    result: buffer std_logic_vector(31 downto 0);
    zero: out std_logic
  );
end;

architecture behavior of alu is
begin
  process(a, b, alucontrol)
    begin case alucontrol is
      when "000" => result <= a and b;
      when "001" => result <= a or b;
      when "010" => result <= std_logic_vector(unsigned(a) + unsigned(b));
      when "110" => result <= std_logic_vector(unsigned(a) - unsigned(b));
      when "111" =>
        if(a < b) then
          result <= x"00000001";
        else
          result <= x"00000000";
        end if;
      when others => null;
    end case;
  end process;
  zero <= '1' when result = x"00000000" else '0';
end;

HAPRA/Hapra9/alu/alu_tb.vhdl
library ieee;
use ieee.std_logic_1164.all;

entity alu_tb is 
end alu_tb;

architecture behavior of alu_tb is

    component alu is 
    port(
   	 a: in std_logic_vector(31 downto 0);
	 b: in std_logic_vector(31 downto 0);
	 alucontrol: in std_logic_vector(2 downto 0);
         result: buffer std_logic_vector(31 downto 0);
	 zero: out std_logic
    );
    end component;
    
    signal a : std_logic_vector(31 downto 0) := (others => '0');
    signal b : std_logic_vector(31 downto 0) := (others => '0');
    signal alucontrol : std_logic_vector(2 downto 0) := (others => '0');  
    signal result : std_logic_vector(31 downto 0) := (others => '0');
    signal zero : std_logic := '0';

begin
    alu_1 : alu port map (a => a, b => b, alucontrol => alucontrol, result => result, zero => zero);


    process begin
    
	wait for 10 ns;
	a <= "01101011001010110110101100101011";
	b <= "11001100101010101001001000111010";
	alucontrol <= "000"; -- 1 case
	wait for 10 ns;
	alucontrol <= "001"; -- 2 case
	wait for 10 ns;
	alucontrol <= "010"; -- 3 case
	wait for 10 ns;
	alucontrol <= "001"; -- 4 case
	wait for 10 ns;
	alucontrol <= "110"; -- 5 case
	wait for 10 ns;
	alucontrol <= "111"; -- 6 case
	wait for 10 ns;
	alucontrol <= "011"; -- others
	wait for 10 ns;
	a <= "11111111111111110000000000000000";
	b <= "00000000000000001111111111111111";
	alucontrol <= "000";
	wait for 10 ns;
	
        wait;
    end process; 
    
end behavior;

HAPRA/Hapra9/alu/testbench.vcd
$date
  Tue Jan 14 17:29:29 2025
$end
$version
  GHDL v0
$end
$timescale
  1 fs
$end
$scope module standard $end
$upscope $end
$scope module std_logic_1164 $end
$upscope $end
$scope module numeric_std $end
$upscope $end
$scope module alu_tb $end
$var reg 32 ! a[31:0] $end
$var reg 32 " b[31:0] $end
$var reg 3 # alucontrol[2:0] $end
$var reg 32 $ result[31:0] $end
$var reg 1 % zero $end
$scope module alu_1 $end
$var reg 32 & a[31:0] $end
$var reg 32 ' b[31:0] $end
$var reg 3 ( alucontrol[2:0] $end
$var reg 32 ) result[31:0] $end
$var reg 1 * zero $end
$upscope $end
$upscope $end
$enddefinitions $end
#0
b00000000000000000000000000000000 !
b00000000000000000000000000000000 "
b000 #
b00000000000000000000000000000000 $
1%
b00000000000000000000000000000000 &
b00000000000000000000000000000000 '
b000 (
b00000000000000000000000000000000 )
1*
#10000000
b01101011001010110110101100101011 !
b11001100101010101001001000111010 "
b01001000001010100000001000101010 $
0%
b01101011001010110110101100101011 &
b11001100101010101001001000111010 '
b01001000001010100000001000101010 )
0*
#20000000
b001 #
b11101111101010111111101100111011 $
b001 (
b11101111101010111111101100111011 )
#30000000
b010 #
b00110111110101011111110101100101 $
b010 (
b00110111110101011111110101100101 )
#40000000
b001 #
b11101111101010111111101100111011 $
b001 (
b11101111101010111111101100111011 )
#50000000
b110 #
b10011110100000001101100011110001 $
b110 (
b10011110100000001101100011110001 )
#60000000
b111 #
b00000000000000000000000000000001 $
b111 (
b00000000000000000000000000000001 )
#70000000
b011 #
b011 (
#80000000
b11111111111111110000000000000000 !
b00000000000000001111111111111111 "
b000 #
b00000000000000000000000000000000 $
1%
b11111111111111110000000000000000 &
b00000000000000001111111111111111 '
b000 (
b00000000000000000000000000000000 )
1*
