HAPRA/Hapra6/6.3/jk_flipflop.vhdl
library ieee;
use ieee.std_logic_1164.all;

entity jk_flipflop is
    port(
        j,k, clk, reset : in std_logic;
        Q : out std_logic
    );
end jk_flipflop;


architecture bh of jk_flipflop is
        signal q_int : std_logic;
    begin
        q <= q_int;
        process begin
            wait until rising_edge(clk);
                if (reset = '1') then
                    q_int <= '0';
                elsif (j = '0' and k = '1') then
                    q_int <= '0';
                elsif (j = '1' and k = '0') then
                    q_int <= '1';
                elsif (j = '1' and k = '1') then
                    q_int <= not q_int;
                end if;
        end process;
end bh;

HAPRA/Hapra5/5.3/jk_ff_tb.vhdl
library ieee;
use ieee.std_logic_1164.all;

entity jk_ff_tb is
end jk_ff_tb;

architecture testbench of jk_ff_tb is

component JK_FlipFlop is
    port (
      J,K, clk , reset : in std_logic;
      Q : out std_logic
    );
end component;

signal J,K, clk, reset, Q: std_logic;

begin

jk_ff_1 : JK_FlipFlop port map(J => J, K => K, clk => clk,reset => reset, Q => Q);

  process begin
            
        J <= '0';
        K <= '0';
        clk <= '0';
        reset <= '0';
        wait for 10 ns;
        J <= '0';
        K <= '1';
        clk <= '1';
        reset <= '0';
        wait for 10 ns;
        J <= '1';
        K <= '0';
        clk <= '0';
        wait for 10 ns;
        J <= '1';
        K <= '1';
        clk <= '1';
        wait for 10 ns;
        J <= '1';
        K <= '1';
        clk <= '0';
        reset <= '1';
        wait for 10 ns;
        J <= '1';
        K <= '0';
        clk <= '1';
        wait for 10 ns;
        J <= '0';
        K <= '1';
        clk <= '0';
        wait for 10 ns;
        J <= '0';
        K <= '0';
        clk <= '1';
        wait for 10 ns;
        wait;
    end process;
   
end testbench;

HAPRA/Hapra5/5.3/testbench.vcd
$date
  Tue Nov 19 15:38:30 2024
$end
$version
  GHDL v0
$end
$timescale
  1 fs
$end
$scope module standard $end
$upscope $end
$scope module std_logic_1164 $end
$upscope $end
$scope module jk_ff_tb $end
$var reg 1 ! j $end
$var reg 1 " k $end
$var reg 1 # clk $end
$var reg 1 $ reset $end
$var reg 1 % q $end
$scope module jk_ff_1 $end
$var reg 1 & j $end
$var reg 1 ' k $end
$var reg 1 ( clk $end
$var reg 1 ) reset $end
$var reg 1 * q $end
$var reg 1 + q_int $end
$upscope $end
$upscope $end
$enddefinitions $end
#0
0!
0"
0#
0$
U%
0&
0'
0(
0)
U*
U+
#10000000
1"
1#
0%
1'
1(
0*
0+
#20000000
1!
0"
0#
1&
0'
0(
#30000000
1"
1#
1%
1'
1(
1*
1+
#40000000
0#
1$
0(
1)
#50000000
0"
1#
0%
0'
1(
0*
0+
#60000000
0!
1"
0#
0&
1'
0(
#70000000
0"
1#
0'
1(
