HAPRA/Hapra6/6.1ab/DFlipFlop.vhdl
library ieee;
use ieee.std_logic_1164.all;

entity DFlipFlop is
    port (
      d, clk, reset: in std_logic;
      Q : out std_logic
    );
  end DFlipFlop;

architecture behavioral of DFlipFlop is

-- Verhalten des Flip Flops mit Reset

begin
  process begin
  wait on clk until clk = '1';
      Q <= d and (not reset);
  end process;
end behavioral ;

HAPRA/Hapra6/6.2e/sipo_register.vhdl
library ieee;
use ieee.std_logic_1164.all;

-- ein serieler Input, 8 bit parallel Output
entity sipo_register is
    port(
        serial_in, clear, clock : in std_logic;
        Q : out std_logic_vector(3 downto 0)
    );
end sipo_register;

architecture rtl of sipo_register is
    component DFlipFlop is 
        port (
            d, clk, reset: in std_logic;
            Q : out std_logic
        );
    end component;

signal q1: std_logic;
signal q2: std_logic;   
signal q3: std_logic;
signal q4: std_logic;


begin

flipflop1 : DFlipFlop port map(d => serial_in, clk => clock, reset => clear, Q => q1);
flipflop2 : DFlipFlop port map(d => q1, clk => clock, reset => clear, Q => q2);
flipflop3 : DFlipFlop port map(d => q2, clk => clock, reset => clear, Q => q3);
flipflop4 : DFlipFlop port map(d => q3, clk => clock, reset => clear, Q => q4);

Q(0) <= q1;
Q(1) <= q2;
Q(2) <= q3;
Q(3) <= q4;

end rtl;

HAPRA/Hapra6/6.2e/robot.vhdl
library ieee;
use ieee.std_logic_1164.all;

entity robot is 
    port(
        pattern : in std_logic_vector(3 downto 0); 
        sensor, reset, clock : in std_logic; 
        alarm : out std_logic 
    );
end robot;

architecture rtl of robot is
 
    component sipo_register is
        port(
            serial_in, clear, clock : in std_logic;
            Q : out std_logic_vector(3 downto 0) 
        );
    end component;
 
    signal serial_in : std_logic;  
    signal Q : std_logic_vector(3 downto 0); 

begin
    
    schieb1 : sipo_register port map(serial_in => sensor, clear => reset, clock => clock, Q => Q);

    process(clock)
    begin
        if rising_edge(clock) then
            if Q = pattern then
                alarm <= '1'; 
            else
                alarm <= '0'; 
            end if;
        end if;
    end process;

end rtl;

HAPRA/Hapra6/6.2e/robot_tb.vhdl
library ieee;
use ieee.std_logic_1164.all;

entity robot_tb is 
end robot_tb;

architecture rtl of robot_tb is

    component robot is 
    port(
        pattern : in std_logic_vector(3 downto 0); 
        sensor, reset, clock : in std_logic;
        alarm : out std_logic
    );
    end component;
    

    signal alarm : std_logic;     
    signal reset : std_logic; 
    signal sensor : std_logic; 
    signal clock : std_logic; 
    signal pattern : std_logic_vector(3 downto 0); 
begin
    rbt : robot port map (sensor => sensor, reset => reset, clock => clock, alarm => alarm, pattern => pattern);


    process begin
        ------Initialisierung--
        pattern(0) <= '1';
        pattern(1) <= '0';
        pattern(2) <= '1';
        pattern(3) <= '1';

        sensor <= '0';
        reset <= '1';
        clock <= '1'; 
        wait for 10 ns; 
        -----------------------
        reset <= '0'; 
        clock <= '0'; 
        wait for 10 ns; 
        -----------------------

        -- Wir lesen die Bitfolge "101101111" bitweise in sensor ein 
        -- Nachdem "1011" erkannt wurde wird das Pattern auf "1101" gesetzt
        
        -----------------------
        sensor <= '1'; 
        clock <= '1'; 
        wait for 10 ns;
        clock <= '0';
        wait for 10 ns; 
        -----------------------
        sensor <= '0'; 
        clock <= '1'; 
        wait for 10 ns;
        clock <= '0';
        wait for 10 ns;
        -----------------------
        sensor <= '1'; 
        clock <= '1'; 
        wait for 10 ns;
        clock <= '0';
        wait for 10 ns;
        -----------------------
        sensor <= '1'; 
        clock <= '1'; 
        wait for 10 ns;
        clock <= '0';
        wait for 10 ns;
        -- hier sollte alarm = 1 sein (1011 wurde erkannt)
        -----------------------


        -- das zu suchende Pattern wird auf 1101 gesetzt 
        pattern(0) <= '1';
        pattern(1) <= '1';
        pattern(2) <= '0';
        pattern(3) <= '1';

        -----------------------
        sensor <= '0'; 
        clock <= '1'; 
        wait for 10 ns;
        clock <= '0';
        wait for 10 ns;
        -----------------------
        sensor <= '1'; 
        clock <= '1'; 
        wait for 10 ns;
        clock <= '0';
        wait for 10 ns;
        -- hier sollte alarm = 1 sein (1101 wurde erkannt, die 11 zu beginn wurden schon vor dem neu setzen des patterns gelesen)
        -----------------------
        sensor <= '1'; 
        clock <= '1'; 
        wait for 10 ns;
        clock <= '0';
        wait for 10 ns;
        -----------------------
        sensor <= '0'; 
        clock <= '1'; 
        wait for 10 ns;
        clock <= '0';
        wait for 10 ns;
        -----------------------
        sensor <= '1'; 
        clock <= '1'; 
        wait for 10 ns;
        clock <= '0';
        wait for 10 ns;
        -- hier sollte alarm = 1 sein (1101 wurde erkannt)

        wait;
    end process; 
    
end rtl;

HAPRA/Hapra6/6.2e/testbench.vcd
$date
  Tue Nov 26 15:48:19 2024
$end
$version
  GHDL v0
$end
$timescale
  1 fs
$end
$scope module standard $end
$upscope $end
$scope module std_logic_1164 $end
$upscope $end
$scope module robot_tb $end
$var reg 1 ! alarm $end
$var reg 1 " reset $end
$var reg 1 # sensor $end
$var reg 1 $ clock $end
$var reg 4 % pattern[3:0] $end
$scope module rbt $end
$var reg 4 & pattern[3:0] $end
$var reg 1 ' sensor $end
$var reg 1 ( reset $end
$var reg 1 ) clock $end
$var reg 1 * alarm $end
$var reg 1 + serial_in $end
$var reg 4 , q[3:0] $end
$scope module schieb1 $end
$var reg 1 - serial_in $end
$var reg 1 . clear $end
$var reg 1 / clock $end
$var reg 4 0 q[3:0] $end
$var reg 1 1 q1 $end
$var reg 1 2 q2 $end
$var reg 1 3 q3 $end
$var reg 1 4 q4 $end
$scope module flipflop1 $end
$var reg 1 5 d $end
$var reg 1 6 clk $end
$var reg 1 7 reset $end
$var reg 1 8 q $end
$upscope $end
$scope module flipflop2 $end
$var reg 1 9 d $end
$var reg 1 : clk $end
$var reg 1 ; reset $end
$var reg 1 < q $end
$upscope $end
$scope module flipflop3 $end
$var reg 1 = d $end
$var reg 1 > clk $end
$var reg 1 ? reset $end
$var reg 1 @ q $end
$upscope $end
$scope module flipflop4 $end
$var reg 1 A d $end
$var reg 1 B clk $end
$var reg 1 C reset $end
$var reg 1 D q $end
$upscope $end
$upscope $end
$upscope $end
$upscope $end
$enddefinitions $end
#0
U!
1"
0#
1$
b1101 %
b1101 &
0'
1(
1)
U*
U+
b0000 ,
0-
1.
1/
b0000 0
01
02
03
04
05
16
17
08
09
1:
1;
0<
0=
1>
1?
0@
0A
1B
1C
0D
#10000000
0"
0$
0(
0)
0.
0/
06
07
0:
0;
0>
0?
0B
0C
#20000000
0!
1#
1$
1'
1)
0*
b0001 ,
1-
1/
b0001 0
11
15
16
18
19
1:
1>
1B
#30000000
0$
0)
0/
06
0:
0>
0B
#40000000
0#
1$
0'
1)
b0010 ,
0-
1/
b0010 0
01
12
05
16
08
09
1:
1<
1=
1>
1B
#50000000
0$
0)
0/
06
0:
0>
0B
#60000000
1#
1$
1'
1)
b0101 ,
1-
1/
b0101 0
11
02
13
15
16
18
19
1:
0<
0=
1>
1@
1A
1B
#70000000
0$
0)
0/
06
0:
0>
0B
#80000000
1$
1)
b1011 ,
1/
b1011 0
12
03
14
16
1:
1<
1=
1>
0@
0A
1B
1D
#90000000
0$
0)
0/
06
0:
0>
0B
#100000000
1!
0#
1$
b1011 %
b1011 &
0'
1)
1*
b0110 ,
0-
1/
b0110 0
01
13
04
05
16
08
09
1:
1>
1@
1A
1B
0D
#110000000
0$
0)
0/
06
0:
0>
0B
#120000000
0!
1#
1$
1'
1)
0*
b1101 ,
1-
1/
b1101 0
11
02
14
15
16
18
19
1:
0<
0=
1>
1B
1D
#130000000
0$
0)
0/
06
0:
0>
0B
#140000000
1$
1)
b1011 ,
1/
b1011 0
12
03
16
1:
1<
1=
1>
0@
0A
1B
#150000000
0$
0)
0/
06
0:
0>
0B
#160000000
1!
0#
1$
0'
1)
1*
b0110 ,
0-
1/
b0110 0
01
13
04
05
16
08
09
1:
1>
1@
1A
1B
0D
#170000000
0$
0)
0/
06
0:
0>
0B
#180000000
0!
1#
1$
1'
1)
0*
b1101 ,
1-
1/
b1101 0
11
02
14
15
16
18
19
1:
0<
0=
1>
1B
1D
