HAPRA/Hapra6/6.1ab/DFlipFlop.vhdl
library ieee;
use ieee.std_logic_1164.all;

entity DFlipFlop is
    port (
      d, clk, reset: in std_logic;
      Q : out std_logic
    );
  end DFlipFlop;

architecture behavioral of DFlipFlop is

-- Verhalten des Flip Flops mit Reset

begin
  process begin
  wait on clk until clk = '1';
      Q <= d and (not reset);
  end process;
end behavioral ;

HAPRA/Hapra6/6.2e/sipo_register.vhdl
library ieee;
use ieee.std_logic_1164.all;

-- ein serieler Input, 8 bit parallel Output
entity sipo_register is
    port(
        serial_in, clear, clock : in std_logic;
        Q : out std_logic_vector(3 downto 0)
    );
end sipo_register;

architecture rtl of sipo_register is
    component DFlipFlop is 
        port (
            d, clk, reset: in std_logic;
            Q : out std_logic
        );
    end component;

signal q1: std_logic;
signal q2: std_logic;   
signal q3: std_logic;
signal q4: std_logic;


begin

flipflop1 : DFlipFlop port map(d => serial_in, clk => clock, reset => clear, Q => q1);
flipflop2 : DFlipFlop port map(d => q1, clk => clock, reset => clear, Q => q2);
flipflop3 : DFlipFlop port map(d => q2, clk => clock, reset => clear, Q => q3);
flipflop4 : DFlipFlop port map(d => q3, clk => clock, reset => clear, Q => q4);

Q(0) <= q1;
Q(1) <= q2;
Q(2) <= q3;
Q(3) <= q4;

end rtl;

HAPRA/Hapra6/6.1ab/sipo_register_tb.vhdl
library ieee;
use ieee.std_logic_1164.all;

entity sipo_register_tb is 
end sipo_register_tb;

architecture rtl of sipo_register_tb is

component sipo_register is
    port(
        serial_in, clear, clock : in std_logic;
        Q : out std_logic_vector(3 downto 0)
    );
end component;
    
signal serial_data_input, clear, clock : std_logic;
signal Q : std_logic_vector(3 downto 0);

begin
   

sipo1 : sipo_register port map(serial_in => serial_data_input, clear => clear, clock => clock, Q => Q);


    process begin
       -- SIPO initialisieren indem man es zurueck setzt
	  clock <= '0'; 
	  clear <= '0';
	  serial_data_input <= '0';
	  wait for 10 ns;
	  --Zuruecksetzen.
	  clear <= '1';
	  clock <= '1';
	
	  wait for 10 ns;
	  clock <= '0'; 
	  clear <= '0';
	  wait for 10 ns;

        --Uebergebe die Bitsequenz 1000 
        --erstes Bit
        serial_data_input <= '1';
	    clock <= '1';
	    wait for 10 ns;
	    clock <= '0';
	    wait for 10 ns;

	    serial_data_input <= '0';
	    clock <= '1';
	    wait for 10 ns;
	    clock <= '0';
	    wait for 10 ns;

	    serial_data_input <= '0';
	    clock <= '1';
	    wait for 10 ns;
	    clock <= '0';
	    wait for 10 ns;

	    serial_data_input <= '0';
	    clock <= '1';
	    wait for 10 ns;
	    clock <= '0';
	    wait for 30 ns;
        --Zuruecksetzen.
	   clear <= '1';
	   clock <= '1';
	  serial_data_input <= '0';
	  wait for 10 ns;
	  clock <= '0'; 
	  clear <= '0';
	  wait for 10 ns;
        
        --Test Fall (0110)
	  serial_data_input <= '0';
	  clock <= '1';
          wait for 10 ns;
          clock <= '0';
          wait for 10 ns;

         serial_data_input <= '1';
         clock <= '1';
         wait for 10 ns;
         clock <= '0';
         wait for 10 ns;

	 serial_data_input <= '1';    
	 clock <= '1';
	 wait for 10 ns; 
	 clock <= '0';
         wait for 10 ns;

	 serial_data_input <= '0';
         clock <= '1';
         wait for 10 ns;
         clock <= '0';
         wait for 30 ns;
        
        wait;
    end process; 
    
end rtl;

HAPRA/Hapra6/6.1ab/testbench.vcd
$date
  Tue Nov 26 13:41:53 2024
$end
$version
  GHDL v0
$end
$timescale
  1 fs
$end
$scope module standard $end
$upscope $end
$scope module std_logic_1164 $end
$upscope $end
$scope module sipo_register_tb $end
$var reg 1 ! serial_data_input $end
$var reg 1 " clear $end
$var reg 1 # clock $end
$var reg 4 $ q[3:0] $end
$scope module sipo1 $end
$var reg 1 % serial_in $end
$var reg 1 & clear $end
$var reg 1 ' clock $end
$var reg 4 ( q[3:0] $end
$var reg 1 ) q1 $end
$var reg 1 * q2 $end
$var reg 1 + q3 $end
$var reg 1 , q4 $end
$scope module flipflop1 $end
$var reg 1 - d $end
$var reg 1 . clk $end
$var reg 1 / reset $end
$var reg 1 0 q $end
$upscope $end
$scope module flipflop2 $end
$var reg 1 1 d $end
$var reg 1 2 clk $end
$var reg 1 3 reset $end
$var reg 1 4 q $end
$upscope $end
$scope module flipflop3 $end
$var reg 1 5 d $end
$var reg 1 6 clk $end
$var reg 1 7 reset $end
$var reg 1 8 q $end
$upscope $end
$scope module flipflop4 $end
$var reg 1 9 d $end
$var reg 1 : clk $end
$var reg 1 ; reset $end
$var reg 1 < q $end
$upscope $end
$upscope $end
$upscope $end
$enddefinitions $end
#0
0!
0"
0#
bUUUU $
0%
0&
0'
bUUUU (
U)
U*
U+
U,
0-
0.
0/
U0
U1
02
03
U4
U5
06
07
U8
U9
0:
0;
U<
#10000000
1"
1#
b0000 $
1&
1'
b0000 (
0)
0*
0+
0,
1.
1/
00
01
12
13
04
05
16
17
08
09
1:
1;
0<
#20000000
0"
0#
0&
0'
0.
0/
02
03
06
07
0:
0;
#30000000
1!
1#
b0001 $
1%
1'
b0001 (
1)
1-
1.
10
11
12
16
1:
#40000000
0#
0'
0.
02
06
0:
#50000000
0!
1#
b0010 $
0%
1'
b0010 (
0)
1*
0-
1.
00
01
12
14
15
16
1:
#60000000
0#
0'
0.
02
06
0:
#70000000
1#
b0100 $
1'
b0100 (
0*
1+
1.
12
04
05
16
18
19
1:
#80000000
0#
0'
0.
02
06
0:
#90000000
1#
b1000 $
1'
b1000 (
0+
1,
1.
12
16
08
09
1:
1<
#100000000
0#
0'
0.
02
06
0:
#130000000
1"
1#
b0000 $
1&
1'
b0000 (
0,
1.
1/
12
13
16
17
1:
1;
0<
#140000000
0"
0#
0&
0'
0.
0/
02
03
06
07
0:
0;
#150000000
1#
1'
1.
12
16
1:
#160000000
0#
0'
0.
02
06
0:
#170000000
1!
1#
b0001 $
1%
1'
b0001 (
1)
1-
1.
10
11
12
16
1:
#180000000
0#
0'
0.
02
06
0:
#190000000
1#
b0011 $
1'
b0011 (
1*
1.
12
14
15
16
1:
#200000000
0#
0'
0.
02
06
0:
#210000000
0!
1#
b0110 $
0%
1'
b0110 (
0)
1+
0-
1.
00
01
12
16
18
19
1:
