HAPRA/Hapra2/2.3d_transport/andgate.vhdl
library ieee;
use ieee.std_logic_1164.all;


entity andgate is

  port (
    input1 : in std_logic;
    input2 : in std_logic;
    and_result : out std_logic
  );
end andgate;


architecture rtl of andgate is

  signal and_gate : std_logic;
begin
  
  --Hier habe ich die Delay mit transport gemacht 
  and_gate <= transport input1 and input2 after 15 ns;

  and_result <= and_gate;
end rtl;

HAPRA/Hapra2/2.3e/andgate_tb.vhdl
library ieee;
use ieee.std_logic_1164.all;

-- create testbench for and_gate
-- can be left empty, since test bench (this file) has no inputs or outputs
entity andgate_tb is
end andgate_tb;

architecture test of andgate_tb is
  -- component declaration, so that it can be instantiated later
  -- must have same name and port list as the entity
  component andgate
      port (
        input1 : in std_logic;
        input2 : in std_logic;
        and_result : out std_logic
      );
  end component;
-- define the signals that will be used in test
  signal a, b, c : std_logic;
-- begin test code
begin
  -- creates an instance of andgate
  and_g: andgate port map(input1 => a, input2 => b, and_result => c);

  process begin
    a <= '1';
    b <= '0';
    wait for 9 ns;
    a <= '1';
    b <= '1';
    wait for 9 ns;
    a <= '1';
    b <= '0';
    wait for 20 ns;
    a <= '1';
    b <= '1';
    wait for 20 ns;
    a <= 'X';
    b <= 'W';
    wait for 10 ns;
    assert false report "End of test";
    wait;
  end process;
end test;

HAPRA/Hapra2/2.3d_transport/testbench.vcd
$date
  Wed Oct 23 16:21:45 2024
$end
$version
  GHDL v0
$end
$timescale
  1 fs
$end
$scope module standard $end
$upscope $end
$scope module std_logic_1164 $end
$upscope $end
$scope module andgate_tb $end
$var reg 1 ! a $end
$var reg 1 " b $end
$var reg 1 # c $end
$scope module and_g $end
$var reg 1 $ input1 $end
$var reg 1 % input2 $end
$var reg 1 & and_result $end
$var reg 1 ' and_gate $end
$upscope $end
$upscope $end
$enddefinitions $end
#0
1!
0"
U#
1$
0%
U&
U'
#10000000
1"
1%
#15000000
0#
0&
0'
#20000000
0"
0%
#25000000
1#
1&
1'
#30000000
1"
1%
#35000000
0#
0&
0'
#40000000
X!
W"
X$
W%
#45000000
1#
1&
1'
#50000000
#55000000
X#
X&
X'
