HAPRA/Hapra6/6.3/jk_flipflop.vhdl
library ieee;
use ieee.std_logic_1164.all;

entity jk_flipflop is
    port(
        j,k, clk, reset : in std_logic;
        Q : out std_logic
    );
end jk_flipflop;


architecture bh of jk_flipflop is
        signal q_int : std_logic;
    begin
        q <= q_int;
        process begin
            wait until rising_edge(clk);
                if (reset = '1') then
                    q_int <= '0';
                elsif (j = '0' and k = '1') then
                    q_int <= '0';
                elsif (j = '1' and k = '0') then
                    q_int <= '1';
                elsif (j = '1' and k = '1') then
                    q_int <= not q_int;
                end if;
        end process;
end bh;

HAPRA/Hapra6/6.3/sync_counter.vhdl
library ieee;
use ieee.std_logic_1164.all;

entity sync_counter is
    port(
        reset, clk, C, D : in std_logic;
        q1, q0 : out std_logic
    );
end sync_counter;

architecture bh of sync_counter is

    component jk_flipflop is
        port(
            j, k, clk, reset : in std_logic;
            Q : out std_logic
        );
    end component;

    signal j1, k1, j2, k2 : std_logic;
    signal z0, z1 : std_logic := '0';

begin

    j1 <= C and (not D) and not z0; -- hier berehcnen wir j1 (jump1)
    k1 <= (not C) or D or z0; --hier wird k1 berechenent (kill1)

    j2 <= C and (not D) and not z1; --hier brechnen wir j2 (jump2)
    k2 <= (not C) or D or z1; --hier wird k2 brechnet (kill2)
	
	
	--hier wrid beide JK FLipflops verwendent
    flipflop0: jk_flipflop port map(j => j1, k => k1, clk => clk, reset => reset, Q => z0); 
    flipflop1: jk_flipflop port map(j => j2, k => k2, clk => clk, reset => reset, Q => z1);
	
	--ausgang einsetzen
    q0 <= z0;
    q1 <= z1;

end bh;

HAPRA/Hapra6/6.3/sync_counter_tb.vhdl
library ieee;
use ieee.std_logic_1164.all;

entity sync_counter_tb is
end sync_counter_tb;

architecture tb of sync_counter_tb is
    component sync_counter is
        port(
            reset, clk, C, D : in std_logic;
            q1, q0 : out std_logic
        );
    end component;
-- missing
signal  reset, clk, C, D , q1 , q0 : std_logic;
    begin

        rbt : sync_counter port map (reset => reset, clk => clk, C => C, D => D, q1 => q1, q0 => q0);
        process begin
	
    reset <= '1'; --zuerst reseten wir alles 
    C <= '0';
    D <= '0';
    clk <= '0';
    wait for 10 ns;
    C <= '0';
    D <= '0';
    clk <= '1';
    wait for 10 ns ;
    C <= '0';
    D <= '0';
    clk <= '0';
    wait for 10 ns ;
	reset <= '0';
    C <= '1';
    D <= '0';
    clk <= '0';
    wait for 10 ns;
    C <= '1';
    D <= '0';
    clk <= '1';
    wait for 10 ns ;
    C <= '1';
    D <= '0';
    clk <= '0';
    wait for 10 ns ;
    C <= '1';
    D <= '0';
    clk <= '1';
    wait for 10 ns ;
    C <= '1';
    D <= '0';
    clk <= '0';
    wait for 10 ns;
    C <= '1';
    D <= '0';
    clk <= '1';
    wait for 10 ns ;
    C <= '1';
    D <= '0';
    clk <= '0';
    wait for 10 ns ;
    C <= '1';
    D <= '0';
    clk <= '1';
    wait for 10 ns ;
    C <= '1';
    D <= '1';
    clk <= '0';
    wait for 10 ns;
    C <= '1';
    D <= '1';
    clk <= '1';
    wait for 10 ns ;
    C <= '1';
    clk <= '0';
    wait for 10 ns ;
    C <= '1';
    clk <= '1';
    wait for 10 ns ;
    C <= '1';
    D <= '0';
    clk <= '0';
    wait for 10 ns;
    C <= '1';
    clk <= '1';
    wait for 10 ns ;
    C <= '1';
    clk <= '0';
    wait for 10 ns ;
    C <= '1';
    clk <= '1';
    wait for 10 ns ;
    C <= '1';
    clk <= '0';
    wait for 10 ns ;
    C <= '1';
    clk <= '1';
    wait for 10 ns ;
    wait;
        end process;
end tb;

HAPRA/Hapra6/6.3/testbench.vcd
$date
  Fri Nov 29 17:12:20 2024
$end
$version
  GHDL v0
$end
$timescale
  1 fs
$end
$scope module standard $end
$upscope $end
$scope module std_logic_1164 $end
$upscope $end
$scope module sync_counter_tb $end
$var reg 1 ! reset $end
$var reg 1 " clk $end
$var reg 1 # c $end
$var reg 1 $ d $end
$var reg 1 % q1 $end
$var reg 1 & q0 $end
$scope module rbt $end
$var reg 1 ' reset $end
$var reg 1 ( clk $end
$var reg 1 ) c $end
$var reg 1 * d $end
$var reg 1 + q1 $end
$var reg 1 , q0 $end
$var reg 1 - j1 $end
$var reg 1 . k1 $end
$var reg 1 / j2 $end
$var reg 1 0 k2 $end
$var reg 1 1 z0 $end
$var reg 1 2 z1 $end
$scope module flipflop0 $end
$var reg 1 3 j $end
$var reg 1 4 k $end
$var reg 1 5 clk $end
$var reg 1 6 reset $end
$var reg 1 7 q $end
$var reg 1 8 q_int $end
$upscope $end
$scope module flipflop1 $end
$var reg 1 9 j $end
$var reg 1 : k $end
$var reg 1 ; clk $end
$var reg 1 < reset $end
$var reg 1 = q $end
$var reg 1 > q_int $end
$upscope $end
$upscope $end
$upscope $end
$enddefinitions $end
#0
1!
0"
0#
0$
U%
U&
1'
0(
0)
0*
U+
U,
0-
1.
0/
10
U1
U2
03
14
05
16
U7
U8
09
1:
0;
1<
U=
U>
#10000000
1"
0%
0&
1(
0+
0,
01
02
15
07
08
1;
0=
0>
#20000000
0"
0(
05
0;
#30000000
0!
1#
0'
1)
1-
0.
1/
00
13
04
06
19
0:
0<
#40000000
1"
1%
1&
1(
1+
1,
0-
1.
0/
10
11
12
03
14
15
17
18
09
1:
1;
1=
1>
#50000000
0"
0(
05
0;
#60000000
1"
0%
0&
1(
0+
0,
1-
0.
1/
00
01
02
13
04
15
07
08
19
0:
1;
0=
0>
#70000000
0"
0(
05
0;
#80000000
1"
1%
1&
1(
1+
1,
0-
1.
0/
10
11
12
03
14
15
17
18
09
1:
1;
1=
1>
#90000000
0"
0(
05
0;
#100000000
1"
0%
0&
1(
0+
0,
1-
0.
1/
00
01
02
13
04
15
07
08
19
0:
1;
0=
0>
#110000000
0"
1$
0(
1*
0-
1.
0/
10
03
14
05
09
1:
0;
#120000000
1"
1(
15
1;
#130000000
0"
0(
05
0;
#140000000
1"
1(
15
1;
#150000000
0"
0$
0(
0*
1-
0.
1/
00
13
04
05
19
0:
0;
#160000000
1"
1%
1&
1(
1+
1,
0-
1.
0/
10
11
12
03
14
15
17
18
09
1:
1;
1=
1>
#170000000
0"
0(
05
0;
#180000000
1"
0%
0&
1(
0+
0,
1-
0.
1/
00
01
02
13
04
15
07
08
19
0:
1;
0=
0>
#190000000
0"
0(
05
0;
#200000000
1"
1%
1&
1(
1+
1,
0-
1.
0/
10
11
12
03
14
15
17
18
09
1:
1;
1=
1>
