HAPRA/Hapra4/4.0_example/not_gate.vhdl
library ieee;
use ieee.std_logic_1164.all;

entity not_gate is
  port (
    input1 : in std_logic;
    not_output : out std_logic
  );
end not_gate;

architecture rtl of not_gate is
  signal notgate : std_logic;
begin
  notgate <= NOT input1;
  not_output <= notgate;
end rtl;

HAPRA/Hapra4/4.1_mux/or_gate.vhdl
library ieee;
use ieee.std_logic_1164.all;

entity or_gate is
  port (
    input1 : in std_logic;
    input2 : in std_logic;
    input3 : in std_logic;
    input4 : in std_logic;
    or_result : out std_logic
  );
end or_gate;

architecture rtl of or_gate is
  signal orgate : std_logic;
begin
  orgate <= input1 or input2 or input3 or input4;
  or_result <= orgate;
end rtl;

HAPRA/Hapra4/4.1_mux/and_gate.vhdl
library ieee;
use ieee.std_logic_1164.all;

entity and_gate is
  port (
    input1 : in std_logic;
    input2 : in std_logic;
    input3 : in std_logic;
    and_output : out std_logic
  );
end and_gate;

architecture rtl of and_gate is
  signal andgate : std_logic;
begin
  andgate <= input1 and input2 and input3;
  and_output <= andgate;
end rtl;

HAPRA/Hapra4/4.1_mux/mux41.vhdl
LIBRARY IEEE;
USE IEEE.std_logic_1164.ALL;
--the 4:1 multiplexer to be designed consists of four 3-bit inputs, i.e., i0, i1, i2 and i3.
--sel is a 2-bit select signal.
--y is the output.

ENTITY mux41 IS
    PORT (
        i0 : IN std_logic_vector(2 DOWNTO 0); 
        i1 : IN std_logic_vector(2 DOWNTO 0);
        i2 : IN std_logic_vector(2 DOWNTO 0);
        i3 : IN std_logic_vector(2 DOWNTO 0);
        sel : IN std_logic_vector(1 DOWNTO 0); 
        y : OUT std_logic_vector(2 DOWNTO 0)
        );
END mux41;

ARCHITECTURE rtl OF mux41 IS
--you can add more components you need
--you can also increase the number of inputs, e.g., the "and" gate below is extended to a 3-input gate.

    COMPONENT and_gate IS
        PORT (input1 : IN std_logic;
            input2 : IN std_logic;
			input3 : IN std_logic;
            and_output : OUT std_logic);
    END COMPONENT;
    
    COMPONENT or_gate IS
        PORT (input1 : IN std_logic;
            input2 : IN std_logic;
			input3 : IN std_logic;
			input4: in std_logic;
            or_result : OUT std_logic);
    END COMPONENT;
    
    COMPONENT not_gate IS
        PORT (input1 : IN std_logic;
             not_output : OUT std_logic);
    END COMPONENT;
--you can define more signals here if you need, e.g.,:
    signal not_sel : std_logic_vector(1 DOWNTO 0); 
    signal and_output1 : std_logic_vector(2 DOWNTO 0); 
    signal and_output2 : std_logic_vector(2 DOWNTO 0); 
    signal and_output3 : std_logic_vector(2 DOWNTO 0); 
    signal and_output4 : std_logic_vector(2 DOWNTO 0); 
    --signal or_output1: std_logic_vector(2 DOWNTO 0);  56345356456456


BEGIN

--bitwise operation for each logic gate because the input signals are multilple-bit signals.
--please complete the implementation based on the schema you designed.

    
    and_gate_assignment : for i in 0 to 2 generate
        and_output01: and_gate port map(input1 => sel(0), input2 => sel(1), input3 => i3(i), and_output => and_output1(i));
        and_output02: and_gate port map(input1 => sel(1), input2 => not_sel(0), input3 => i2(i), and_output => and_output2(i));
        and_output03: and_gate port map(input1 => sel(0), input2 => not_sel(1), input3 => i1(i), and_output => and_output3(i));
        and_output04: and_gate port map(input1 => not_sel(0), input2 => not_sel(1), input3 => i0(i), and_output => and_output4(i));
     
    end generate and_gate_assignment;
    
    or_gate_assignment : for i in 0 to 2 generate
        or_output1: or_gate port map(input1 => and_output1(i),input2 => and_output2(i), input3 => and_output3(i), input4 => and_output4(i), or_result => y(i));
                        
    end generate or_gate_assignment;
   
   --missing
   -- hier werden die weiteren Komponenten verschaltet
   not_sel5: not_gate port map(input1 => sel(0), not_output => not_sel(0));
   not_sel6: not_gate port map(input1 => sel(1), not_output => not_sel(1));
   

END rtl;

HAPRA/Hapra4/4.1_mux/mux81.vhdl
LIBRARY IEEE;
USE IEEE.std_logic_1164.ALL;


ENTITY mux81 IS
    PORT (
        i0_81 : IN std_logic_vector(2 DOWNTO 0); 
        i1_81 : IN std_logic_vector(2 DOWNTO 0);
        i2_81 : IN std_logic_vector(2 DOWNTO 0);
        i3_81 : IN std_logic_vector(2 DOWNTO 0);
        i4_81 : IN std_logic_vector(2 DOWNTO 0);
        i5_81 : IN std_logic_vector(2 DOWNTO 0);
        i6_81 : IN std_logic_vector(2 DOWNTO 0);
        i7_81 : IN std_logic_vector(2 DOWNTO 0);
        sel_81 : IN std_logic_vector(2 DOWNTO 0); 
        y_81 : OUT std_logic_vector(2 DOWNTO 0));
END mux81;

ARCHITECTURE rtl OF mux81 IS

    COMPONENT mux41 IS
        PORT (
            i0 : IN std_logic_vector(2 DOWNTO 0); 
            i1 : IN std_logic_vector(2 DOWNTO 0);
            i2 : IN std_logic_vector(2 DOWNTO 0);
            i3 : IN std_logic_vector(2 DOWNTO 0);
            sel : IN std_logic_vector(1 DOWNTO 0); 
            y : OUT std_logic_vector(2 DOWNTO 0)
        );
    END COMPONENT;
    
    -- weitere Komponenten 
    
    
    -- Signale
    signal multi_output1 : std_logic_vector(2 DOWNTO 0); 
    signal multi_output2 : std_logic_vector(2 DOWNTO 0); 
    signal multi_output3 : std_logic_vector(2 DOWNTO 0); 
    signal multi_output4 : std_logic_vector(2 DOWNTO 0); 
 
begin

    --missing;
    -- hier werden die einzelnen Komponenten verschaltet
    multiplex1: mux41 port map(i0 => i0_81, i1 => i1_81, i2 => i2_81, i3 => i3_81, sel => sel_81(1 downto 0), y => multi_output1);
    multiplex2: mux41 port map(i0 => i4_81, i1 => i5_81, i2 => i6_81, i3 => i7_81, sel => sel_81(1 downto 0), y => multi_output2);
    mul_assignment : for i in 0 to 2 generate
        multi_output3(i) <= multi_output1(i) and not (sel_81(2));
        multi_output4(i) <= multi_output2(i) and sel_81(2);
        
    end generate mul_assignment;
    
    mul_or_assignment : for i in 0 to 2 generate
        y_81(i) <= multi_output3(i) or multi_output4(i);
        
    end generate mul_or_assignment;
    

end rtl;

HAPRA/Hapra4/4.1_mux/mux81_tb.vhdl
library ieee;
use ieee.std_logic_1164.all;

entity mux81_tb is
end mux81_tb;

architecture testbench of mux81_tb is
  component mux81
    port (i0_81 : IN std_logic_vector(2 DOWNTO 0); 
        i1_81 : IN std_logic_vector(2 DOWNTO 0);
        i2_81 : IN std_logic_vector(2 DOWNTO 0);
        i3_81 : IN std_logic_vector(2 DOWNTO 0);
        i4_81 : IN std_logic_vector(2 DOWNTO 0);
        i5_81 : IN std_logic_vector(2 DOWNTO 0);
        i6_81 : IN std_logic_vector(2 DOWNTO 0);
        i7_81 : IN std_logic_vector(2 DOWNTO 0);
        sel_81 : IN std_logic_vector(2 DOWNTO 0); 
        y_81 : OUT std_logic_vector(2 DOWNTO 0)
        );
  end component;

--missing (Signale)

        signal i0_81 :  std_logic_vector(2 DOWNTO 0); 
        signal i1_81 :  std_logic_vector(2 DOWNTO 0);
        signal i2_81 : std_logic_vector(2 DOWNTO 0);
        signal i3_81 :  std_logic_vector(2 DOWNTO 0);
        signal i4_81 :  std_logic_vector(2 DOWNTO 0); 
        signal i5_81 :  std_logic_vector(2 DOWNTO 0);
        signal i6_81 : std_logic_vector(2 DOWNTO 0);
        signal i7_81 :  std_logic_vector(2 DOWNTO 0);
        signal sel_81 : std_logic_vector(2 DOWNTO 0); 
        signal y_81 : std_logic_vector(2 DOWNTO 0);


begin
    multiplex: mux81 port map(i0_81 => i0_81, i1_81 => i1_81, i2_81 => i2_81, i3_81 => i3_81, i4_81 => i4_81, i5_81 => i5_81, i6_81 => i6_81, i7_81 => i7_81 ,sel_81 => sel_81, y_81 => y_81);



    -- 
    process begin
    -- Die vorgegebenen Werte werden an die Eingaenge des 8:1 Mux angelegt
        i0_81 <= "000";
        i1_81 <= "001";
        i2_81 <= "010";
        i3_81 <= "011";
        i4_81 <= "100";
        i5_81 <= "101";
        i6_81 <= "110";
        i7_81 <= "111";
        
    -- Die Eingaenge werden der Reihe nach durchgeschaltet    
        sel_81 <= "000";
        wait for 10 ns;
        sel_81 <= "001";
        wait for 10 ns;
        sel_81 <= "010";
        wait for 10 ns;
        sel_81 <= "011";
         wait for 10 ns;
        sel_81 <= "100";
        wait for 10 ns;
        sel_81 <= "101";
        wait for 10 ns;
        sel_81 <= "110";
        wait for 10 ns;
        sel_81 <= "111";
        wait for 10 ns;
        wait;
    end process;
end testbench;

HAPRA/Hapra4/4.1_mux/testbench.vcd
$date
  Wed Nov  6 16:25:26 2024
$end
$version
  GHDL v0
$end
$timescale
  1 fs
$end
$scope module standard $end
$upscope $end
$scope module std_logic_1164 $end
$upscope $end
$scope module mux81_tb $end
$var reg 3 ! i0_81[2:0] $end
$var reg 3 " i1_81[2:0] $end
$var reg 3 # i2_81[2:0] $end
$var reg 3 $ i3_81[2:0] $end
$var reg 3 % i4_81[2:0] $end
$var reg 3 & i5_81[2:0] $end
$var reg 3 ' i6_81[2:0] $end
$var reg 3 ( i7_81[2:0] $end
$var reg 3 ) sel_81[2:0] $end
$var reg 3 * y_81[2:0] $end
$scope module multiplex $end
$var reg 3 + i0_81[2:0] $end
$var reg 3 , i1_81[2:0] $end
$var reg 3 - i2_81[2:0] $end
$var reg 3 . i3_81[2:0] $end
$var reg 3 / i4_81[2:0] $end
$var reg 3 0 i5_81[2:0] $end
$var reg 3 1 i6_81[2:0] $end
$var reg 3 2 i7_81[2:0] $end
$var reg 3 3 sel_81[2:0] $end
$var reg 3 4 y_81[2:0] $end
$var reg 3 5 multi_output1[2:0] $end
$var reg 3 6 multi_output2[2:0] $end
$var reg 3 7 multi_output3[2:0] $end
$var reg 3 8 multi_output4[2:0] $end
$scope module multiplex1 $end
$var reg 3 9 i0[2:0] $end
$var reg 3 : i1[2:0] $end
$var reg 3 ; i2[2:0] $end
$var reg 3 < i3[2:0] $end
$var reg 2 = sel[1:0] $end
$var reg 3 > y[2:0] $end
$var reg 2 ? not_sel[1:0] $end
$var reg 3 @ and_output1[2:0] $end
$var reg 3 A and_output2[2:0] $end
$var reg 3 B and_output3[2:0] $end
$var reg 3 C and_output4[2:0] $end
$scope module and_gate_assignment(0) $end
$scope module and_output01 $end
$var reg 1 D input1 $end
$var reg 1 E input2 $end
$var reg 1 F input3 $end
$var reg 1 G and_output $end
$var reg 1 H andgate $end
$upscope $end
$scope module and_output02 $end
$var reg 1 I input1 $end
$var reg 1 J input2 $end
$var reg 1 K input3 $end
$var reg 1 L and_output $end
$var reg 1 M andgate $end
$upscope $end
$scope module and_output03 $end
$var reg 1 N input1 $end
$var reg 1 O input2 $end
$var reg 1 P input3 $end
$var reg 1 Q and_output $end
$var reg 1 R andgate $end
$upscope $end
$scope module and_output04 $end
$var reg 1 S input1 $end
$var reg 1 T input2 $end
$var reg 1 U input3 $end
$var reg 1 V and_output $end
$var reg 1 W andgate $end
$upscope $end
$upscope $end
$scope module and_gate_assignment(1) $end
$scope module and_output01 $end
$var reg 1 X input1 $end
$var reg 1 Y input2 $end
$var reg 1 Z input3 $end
$var reg 1 [ and_output $end
$var reg 1 \ andgate $end
$upscope $end
$scope module and_output02 $end
$var reg 1 ] input1 $end
$var reg 1 ^ input2 $end
$var reg 1 _ input3 $end
$var reg 1 ` and_output $end
$var reg 1 a andgate $end
$upscope $end
$scope module and_output03 $end
$var reg 1 b input1 $end
$var reg 1 c input2 $end
$var reg 1 d input3 $end
$var reg 1 e and_output $end
$var reg 1 f andgate $end
$upscope $end
$scope module and_output04 $end
$var reg 1 g input1 $end
$var reg 1 h input2 $end
$var reg 1 i input3 $end
$var reg 1 j and_output $end
$var reg 1 k andgate $end
$upscope $end
$upscope $end
$scope module and_gate_assignment(2) $end
$scope module and_output01 $end
$var reg 1 l input1 $end
$var reg 1 m input2 $end
$var reg 1 n input3 $end
$var reg 1 o and_output $end
$var reg 1 p andgate $end
$upscope $end
$scope module and_output02 $end
$var reg 1 q input1 $end
$var reg 1 r input2 $end
$var reg 1 s input3 $end
$var reg 1 t and_output $end
$var reg 1 u andgate $end
$upscope $end
$scope module and_output03 $end
$var reg 1 v input1 $end
$var reg 1 w input2 $end
$var reg 1 x input3 $end
$var reg 1 y and_output $end
$var reg 1 z andgate $end
$upscope $end
$scope module and_output04 $end
$var reg 1 { input1 $end
$var reg 1 | input2 $end
$var reg 1 } input3 $end
$var reg 1 !" and_output $end
$var reg 1 "" andgate $end
$upscope $end
$upscope $end
$scope module or_gate_assignment(0) $end
$scope module or_output1 $end
$var reg 1 #" input1 $end
$var reg 1 $" input2 $end
$var reg 1 %" input3 $end
$var reg 1 &" input4 $end
$var reg 1 '" or_result $end
$var reg 1 (" orgate $end
$upscope $end
$upscope $end
$scope module or_gate_assignment(1) $end
$scope module or_output1 $end
$var reg 1 )" input1 $end
$var reg 1 *" input2 $end
$var reg 1 +" input3 $end
$var reg 1 ," input4 $end
$var reg 1 -" or_result $end
$var reg 1 ." orgate $end
$upscope $end
$upscope $end
$scope module or_gate_assignment(2) $end
$scope module or_output1 $end
$var reg 1 /" input1 $end
$var reg 1 0" input2 $end
$var reg 1 1" input3 $end
$var reg 1 2" input4 $end
$var reg 1 3" or_result $end
$var reg 1 4" orgate $end
$upscope $end
$upscope $end
$scope module not_sel5 $end
$var reg 1 5" input1 $end
$var reg 1 6" not_output $end
$var reg 1 7" notgate $end
$upscope $end
$scope module not_sel6 $end
$var reg 1 8" input1 $end
$var reg 1 9" not_output $end
$var reg 1 :" notgate $end
$upscope $end
$upscope $end
$scope module multiplex2 $end
$var reg 3 ;" i0[2:0] $end
$var reg 3 <" i1[2:0] $end
$var reg 3 =" i2[2:0] $end
$var reg 3 >" i3[2:0] $end
$var reg 2 ?" sel[1:0] $end
$var reg 3 @" y[2:0] $end
$var reg 2 A" not_sel[1:0] $end
$var reg 3 B" and_output1[2:0] $end
$var reg 3 C" and_output2[2:0] $end
$var reg 3 D" and_output3[2:0] $end
$var reg 3 E" and_output4[2:0] $end
$scope module and_gate_assignment(0) $end
$scope module and_output01 $end
$var reg 1 F" input1 $end
$var reg 1 G" input2 $end
$var reg 1 H" input3 $end
$var reg 1 I" and_output $end
$var reg 1 J" andgate $end
$upscope $end
$scope module and_output02 $end
$var reg 1 K" input1 $end
$var reg 1 L" input2 $end
$var reg 1 M" input3 $end
$var reg 1 N" and_output $end
$var reg 1 O" andgate $end
$upscope $end
$scope module and_output03 $end
$var reg 1 P" input1 $end
$var reg 1 Q" input2 $end
$var reg 1 R" input3 $end
$var reg 1 S" and_output $end
$var reg 1 T" andgate $end
$upscope $end
$scope module and_output04 $end
$var reg 1 U" input1 $end
$var reg 1 V" input2 $end
$var reg 1 W" input3 $end
$var reg 1 X" and_output $end
$var reg 1 Y" andgate $end
$upscope $end
$upscope $end
$scope module and_gate_assignment(1) $end
$scope module and_output01 $end
$var reg 1 Z" input1 $end
$var reg 1 [" input2 $end
$var reg 1 \" input3 $end
$var reg 1 ]" and_output $end
$var reg 1 ^" andgate $end
$upscope $end
$scope module and_output02 $end
$var reg 1 _" input1 $end
$var reg 1 `" input2 $end
$var reg 1 a" input3 $end
$var reg 1 b" and_output $end
$var reg 1 c" andgate $end
$upscope $end
$scope module and_output03 $end
$var reg 1 d" input1 $end
$var reg 1 e" input2 $end
$var reg 1 f" input3 $end
$var reg 1 g" and_output $end
$var reg 1 h" andgate $end
$upscope $end
$scope module and_output04 $end
$var reg 1 i" input1 $end
$var reg 1 j" input2 $end
$var reg 1 k" input3 $end
$var reg 1 l" and_output $end
$var reg 1 m" andgate $end
$upscope $end
$upscope $end
$scope module and_gate_assignment(2) $end
$scope module and_output01 $end
$var reg 1 n" input1 $end
$var reg 1 o" input2 $end
$var reg 1 p" input3 $end
$var reg 1 q" and_output $end
$var reg 1 r" andgate $end
$upscope $end
$scope module and_output02 $end
$var reg 1 s" input1 $end
$var reg 1 t" input2 $end
$var reg 1 u" input3 $end
$var reg 1 v" and_output $end
$var reg 1 w" andgate $end
$upscope $end
$scope module and_output03 $end
$var reg 1 x" input1 $end
$var reg 1 y" input2 $end
$var reg 1 z" input3 $end
$var reg 1 {" and_output $end
$var reg 1 |" andgate $end
$upscope $end
$scope module and_output04 $end
$var reg 1 }" input1 $end
$var reg 1 !# input2 $end
$var reg 1 "# input3 $end
$var reg 1 ## and_output $end
$var reg 1 $# andgate $end
$upscope $end
$upscope $end
$scope module or_gate_assignment(0) $end
$scope module or_output1 $end
$var reg 1 %# input1 $end
$var reg 1 &# input2 $end
$var reg 1 '# input3 $end
$var reg 1 (# input4 $end
$var reg 1 )# or_result $end
$var reg 1 *# orgate $end
$upscope $end
$upscope $end
$scope module or_gate_assignment(1) $end
$scope module or_output1 $end
$var reg 1 +# input1 $end
$var reg 1 ,# input2 $end
$var reg 1 -# input3 $end
$var reg 1 .# input4 $end
$var reg 1 /# or_result $end
$var reg 1 0# orgate $end
$upscope $end
$upscope $end
$scope module or_gate_assignment(2) $end
$scope module or_output1 $end
$var reg 1 1# input1 $end
$var reg 1 2# input2 $end
$var reg 1 3# input3 $end
$var reg 1 4# input4 $end
$var reg 1 5# or_result $end
$var reg 1 6# orgate $end
$upscope $end
$upscope $end
$scope module not_sel5 $end
$var reg 1 7# input1 $end
$var reg 1 8# not_output $end
$var reg 1 9# notgate $end
$upscope $end
$scope module not_sel6 $end
$var reg 1 :# input1 $end
$var reg 1 ;# not_output $end
$var reg 1 <# notgate $end
$upscope $end
$upscope $end
$scope module mul_assignment(0) $end
$upscope $end
$scope module mul_assignment(1) $end
$upscope $end
$scope module mul_assignment(2) $end
$upscope $end
$scope module mul_or_assignment(0) $end
$upscope $end
$scope module mul_or_assignment(1) $end
$upscope $end
$scope module mul_or_assignment(2) $end
$upscope $end
$upscope $end
$upscope $end
$enddefinitions $end
#0
b000 !
b001 "
b010 #
b011 $
b100 %
b101 &
b110 '
b111 (
b000 )
b000 *
b000 +
b001 ,
b010 -
b011 .
b100 /
b101 0
b110 1
b111 2
b000 3
b000 4
b000 5
b100 6
b000 7
b000 8
b000 9
b001 :
b010 ;
b011 <
b00 =
b000 >
b11 ?
b000 @
b000 A
b000 B
b000 C
0D
0E
1F
0G
0H
0I
1J
0K
0L
0M
0N
1O
1P
0Q
0R
1S
1T
0U
0V
0W
0X
0Y
1Z
0[
0\
0]
1^
1_
0`
0a
0b
1c
0d
0e
0f
1g
1h
0i
0j
0k
0l
0m
0n
0o
0p
0q
1r
0s
0t
0u
0v
1w
0x
0y
0z
1{
1|
0}
0!"
0""
0#"
0$"
0%"
0&"
0'"
0("
0)"
0*"
0+"
0,"
0-"
0."
0/"
00"
01"
02"
03"
04"
05"
16"
17"
08"
19"
1:"
b100 ;"
b101 <"
b110 ="
b111 >"
b00 ?"
b100 @"
b11 A"
b000 B"
b000 C"
b000 D"
b100 E"
0F"
0G"
1H"
0I"
0J"
0K"
1L"
0M"
0N"
0O"
0P"
1Q"
1R"
0S"
0T"
1U"
1V"
0W"
0X"
0Y"
0Z"
0["
1\"
0]"
0^"
0_"
1`"
1a"
0b"
0c"
0d"
1e"
0f"
0g"
0h"
1i"
1j"
0k"
0l"
0m"
0n"
0o"
1p"
0q"
0r"
0s"
1t"
1u"
0v"
0w"
0x"
1y"
1z"
0{"
0|"
1}"
1!#
1"#
1##
1$#
0%#
0&#
0'#
0(#
0)#
0*#
0+#
0,#
0-#
0.#
0/#
00#
01#
02#
03#
14#
15#
16#
07#
18#
19#
0:#
1;#
1<#
#10000000
b001 )
b001 *
b001 3
b001 4
b001 5
b101 6
b001 7
b01 =
b001 >
b10 ?
b001 B
1D
0J
1N
1Q
1R
0S
1X
0^
1b
0g
1l
0r
1v
0{
1%"
1'"
1("
15"
06"
07"
b01 ?"
b101 @"
b10 A"
b101 D"
b000 E"
1F"
0L"
1P"
1S"
1T"
0U"
1Z"
0`"
1d"
0i"
1n"
0t"
1x"
1{"
1|"
0}"
0##
0$#
1'#
1)#
1*#
13#
04#
17#
08#
09#
#20000000
b010 )
b010 *
b010 3
b010 4
b010 5
b110 6
b010 7
b10 =
b010 >
b01 ?
b010 A
b000 B
0D
1E
1I
1J
0N
0O
0Q
0R
1S
0T
0X
1Y
1]
1^
1`
1a
0b
0c
1g
0h
0l
1m
1q
1r
0v
0w
1{
0|
0%"
0'"
0("
1*"
1-"
1."
05"
16"
17"
18"
09"
0:"
b10 ?"
b110 @"
b01 A"
b110 C"
b000 D"
0F"
1G"
1K"
1L"
0P"
0Q"
0S"
0T"
1U"
0V"
0Z"
1["
1_"
1`"
1b"
1c"
0d"
0e"
1i"
0j"
0n"
1o"
1s"
1t"
1v"
1w"
0x"
0y"
0{"
0|"
1}"
0!#
0'#
0)#
0*#
1,#
1/#
10#
12#
03#
15#
16#
07#
18#
19#
1:#
0;#
0<#
#30000000
b011 )
b011 *
b011 3
b011 4
b011 5
b111 6
b011 7
b11 =
b011 >
b00 ?
b011 @
b000 A
1D
1G
1H
0J
1N
0S
1X
1[
1\
0^
0`
0a
1b
0g
1l
0r
1v
0{
1#"
1'"
1("
1)"
0*"
15"
06"
07"
b11 ?"
b111 @"
b00 A"
b111 B"
b000 C"
1F"
1I"
1J"
0L"
1P"
0U"
1Z"
1]"
1^"
0`"
0b"
0c"
1d"
0i"
1n"
1q"
1r"
0t"
0v"
0w"
1x"
0}"
1%#
1)#
1*#
1+#
0,#
11#
02#
17#
08#
09#
#40000000
b100 )
b100 *
b100 3
b100 4
b000 5
b100 6
b000 7
b100 8
b00 =
b000 >
b11 ?
b000 @
0D
0E
0G
0H
0I
1J
0N
1O
1S
1T
0X
0Y
0[
0\
0]
1^
0b
1c
1g
1h
0l
0m
0q
1r
0v
1w
1{
1|
0#"
0'"
0("
0)"
0-"
0."
05"
16"
17"
08"
19"
1:"
b00 ?"
b100 @"
b11 A"
b000 B"
b100 E"
0F"
0G"
0I"
0J"
0K"
1L"
0P"
1Q"
1U"
1V"
0Z"
0["
0]"
0^"
0_"
1`"
0d"
1e"
1i"
1j"
0n"
0o"
0q"
0r"
0s"
1t"
0x"
1y"
1}"
1!#
1##
1$#
0%#
0)#
0*#
0+#
0/#
00#
01#
14#
15#
16#
07#
18#
19#
0:#
1;#
1<#
#50000000
b101 )
b101 *
b101 3
b101 4
b001 5
b101 6
b101 8
b01 =
b001 >
b10 ?
b001 B
1D
0J
1N
1Q
1R
0S
1X
0^
1b
0g
1l
0r
1v
0{
1%"
1'"
1("
15"
06"
07"
b01 ?"
b101 @"
b10 A"
b101 D"
b000 E"
1F"
0L"
1P"
1S"
1T"
0U"
1Z"
0`"
1d"
0i"
1n"
0t"
1x"
1{"
1|"
0}"
0##
0$#
1'#
1)#
1*#
13#
04#
17#
08#
09#
#60000000
b110 )
b110 *
b110 3
b110 4
b010 5
b110 6
b110 8
b10 =
b010 >
b01 ?
b010 A
b000 B
0D
1E
1I
1J
0N
0O
0Q
0R
1S
0T
0X
1Y
1]
1^
1`
1a
0b
0c
1g
0h
0l
1m
1q
1r
0v
0w
1{
0|
0%"
0'"
0("
1*"
1-"
1."
05"
16"
17"
18"
09"
0:"
b10 ?"
b110 @"
b01 A"
b110 C"
b000 D"
0F"
1G"
1K"
1L"
0P"
0Q"
0S"
0T"
1U"
0V"
0Z"
1["
1_"
1`"
1b"
1c"
0d"
0e"
1i"
0j"
0n"
1o"
1s"
1t"
1v"
1w"
0x"
0y"
0{"
0|"
1}"
0!#
0'#
0)#
0*#
1,#
1/#
10#
12#
03#
15#
16#
07#
18#
19#
1:#
0;#
0<#
#70000000
b111 )
b111 *
b111 3
b111 4
b011 5
b111 6
b111 8
b11 =
b011 >
b00 ?
b011 @
b000 A
1D
1G
1H
0J
1N
0S
1X
1[
1\
0^
0`
0a
1b
0g
1l
0r
1v
0{
1#"
1'"
1("
1)"
0*"
15"
06"
07"
b11 ?"
b111 @"
b00 A"
b111 B"
b000 C"
1F"
1I"
1J"
0L"
1P"
0U"
1Z"
1]"
1^"
0`"
0b"
0c"
1d"
0i"
1n"
1q"
1r"
0t"
0v"
0w"
1x"
0}"
1%#
1)#
1*#
1+#
0,#
11#
02#
17#
08#
09#
