HAPRA/Hapra9/aludecoder/aludecoder.vhdl
-- Some portions of this code are based on code from the book "Digital Design and Computer Architecture" by Harris and Harris.
-- For educational purposes in TU Dortmund only.

library ieee;
use ieee.std_logic_1164.all;

entity aludecoder is
  port(
    funct: in std_logic_vector(5 downto 0);
    aluop: in std_logic_vector(1 downto 0);
    alucontrol: out std_logic_vector(2 downto 0)
  );
end;

architecture behavior of aludecoder is
begin
  process(funct, aluop) begin
    case aluop is
      when "00" => alucontrol <= "010"; -- add (for lw/sw/addi)
      when "01" => alucontrol <= "110"; -- sub (for beq)
      when others => case funct is
        when "100000" => alucontrol <= "010"; -- add
        when "100010" => alucontrol <= "110"; -- sub
        when "100100" => alucontrol <= "000"; -- and
        when "100101" => alucontrol <= "001"; -- or
        when "101010" => alucontrol <= "111"; -- slt
        when others => alucontrol <= "---"; -- wrong entry in funct
      end case;
    end case;
  end process;
end;

HAPRA/Hapra9/aludecoder/aludecoder_tb.vhdl
library ieee;
use ieee.std_logic_1164.all;

entity aludecoder_tb is
end aludecoder_tb;


architecture structure of aludecoder_tb is 

    component aludecoder is 
    port(
	  funct: in std_logic_vector(5 downto 0);
	  aluop: in std_logic_vector(1 downto 0);
	  alucontrol: out std_logic_vector(2 downto 0)
    );
    end component;
    

    signal funct : std_logic_vector(5 downto 0) := (others => '0');
    signal aluop : std_logic_vector(1 downto 0) := (others => '0');
    signal alucontrol : std_logic_vector(2 downto 0) := (others => '0');
begin
    alucod : aludecoder port map (funct, aluop, alucontrol);
    
process begin

	 ------Initialisierung--
	aluop <= "00";
	wait for 10 ns;
	aluop <= "01";
	wait for 10 ns;
	aluop <= "11"; -- others in aloup, jetzt beginnt die funct case! 
	wait for 10 ns;
	funct <= "100000"; 
	wait for 10 ns;
	funct <= "100010"; 
	wait for 10 ns;
	funct <= "100100"; 
	wait for 10 ns;
	funct <= "100101"; 
	wait for 10 ns;
	funct <= "101010"; 
	wait for 10 ns;
        funct <= "000000"; -- others in funct !!
	wait for 10 ns;
        
        wait;
    end process; 

end structure;

HAPRA/Hapra9/aludecoder/testbench.vcd
$date
  Tue Jan 14 17:30:17 2025
$end
$version
  GHDL v0
$end
$timescale
  1 fs
$end
$scope module standard $end
$upscope $end
$scope module std_logic_1164 $end
$upscope $end
$scope module aludecoder_tb $end
$var reg 6 ! funct[5:0] $end
$var reg 2 " aluop[1:0] $end
$var reg 3 # alucontrol[2:0] $end
$scope module alucod $end
$var reg 6 $ funct[5:0] $end
$var reg 2 % aluop[1:0] $end
$var reg 3 & alucontrol[2:0] $end
$upscope $end
$upscope $end
$enddefinitions $end
#0
b000000 !
b00 "
b010 #
b000000 $
b00 %
b010 &
#10000000
b01 "
b110 #
b01 %
b110 &
#20000000
b11 "
b--- #
b11 %
b--- &
#30000000
b100000 !
b010 #
b100000 $
b010 &
#40000000
b100010 !
b110 #
b100010 $
b110 &
#50000000
b100100 !
b000 #
b100100 $
b000 &
#60000000
b100101 !
b001 #
b100101 $
b001 &
#70000000
b101010 !
b111 #
b101010 $
b111 &
#80000000
b000000 !
b--- #
b000000 $
b--- &
