HAPRA/Hapra3/3.1.2/fa.vhdl
library ieee;
use ieee.std_logic_1164.all;

-- Volladdierer / Fulladder

entity fa is
  port (
    a : in std_logic;
    b : in std_logic;
    cin : in std_logic;
    cout : out std_logic;
    sum: out std_logic

  );
end fa;

architecture rtl of fa is

  signal wire_1 : std_logic;
  signal wire_2 : std_logic;
  signal wire_3 : std_logic;
begin

-- hier sind die zwei outputs (sum,cout)
    
    sum <= a xor b xor cin;
    cout <= (a and b) or ((a xor b) and cin);

end rtl;

HAPRA/Hapra3/3.1.2/fa_tb.vhdl
library ieee;
use ieee.std_logic_1164.all;

entity fa_tb is
end fa_tb;

architecture test of fa_tb is
  component fa
    port (
      a : in std_logic;
      b : in std_logic;
      cin : in std_logic;
      cout : out std_logic;
      sum : out std_logic
    );
  end component;

signal a, b, cin, cout, sum : std_ulogic;
begin

--hier ist die verwendung von full addierer 
  full_adder: fa port map(a => a, b => b, cin => cin, cout => cout, sum => sum);


-- hier sind alle die 8 test cases, die wir testeb müssen
  process begin
  
    a <= '0';
    b <= '0';
    cin <= '0';
    wait for 10 ns;
    a <= '0';
    b <= '0';
    cin <= '1';
    wait for 10 ns;
    a <= '0';
    b <= '1';
    cin <= '0';
    wait for 10 ns;
    a <= '0';
    b <= '1';
    cin <= '1';
    wait for 10 ns;
    a <= '1';
    b <= '0';
    cin <= '0';
    wait for 10 ns;
    a <= '1';
    b <= '0';
    cin <= '1';
    wait for 10 ns;
    a <= '1';
    b <= '1';
    cin <= '0';
    wait for 10 ns;
    a <= '1';
    b <= '1';
    cin <= '1';
    wait for 10 ns;
    
    wait;
  end process;
end test;

HAPRA/Hapra3/3.1.2/testbench.vcd
$date
  Tue Oct 29 17:13:38 2024
$end
$version
  GHDL v0
$end
$timescale
  1 fs
$end
$scope module standard $end
$upscope $end
$scope module std_logic_1164 $end
$upscope $end
$scope module fa_tb $end
$var reg 1 ! a $end
$var reg 1 " b $end
$var reg 1 # cin $end
$var reg 1 $ cout $end
$var reg 1 % sum $end
$scope module full_adder $end
$var reg 1 & a $end
$var reg 1 ' b $end
$var reg 1 ( cin $end
$var reg 1 ) cout $end
$var reg 1 * sum $end
$var reg 1 + wire_1 $end
$var reg 1 , wire_2 $end
$var reg 1 - wire_3 $end
$upscope $end
$upscope $end
$enddefinitions $end
#0
0!
0"
0#
0$
0%
0&
0'
0(
0)
0*
U+
U,
U-
#10000000
1#
1%
1(
1*
#20000000
1"
0#
1'
0(
#30000000
1#
1$
0%
1(
1)
0*
#40000000
1!
0"
0#
0$
1%
1&
0'
0(
0)
1*
#50000000
1#
1$
0%
1(
1)
0*
#60000000
1"
0#
1'
0(
#70000000
1#
1%
1(
1*
